open_scoring/__init__.py
open_scoring/file.py
open_scoring/scoring.py
open_creativity_scoring-1.3.1.dist-info/METADATA
open_creativity_scoring-1.3.1.dist-info/WHEEL
open_creativity_scoring-1.3.1.dist-info/top_level.txt
open_creativity_scoring-1.3.1.dist-info/RECORD
