Metadata-Version: 2.1
Name: open-creativity-scoring
Version: 1.3.1
Summary: Library for scoring Alternate Uses Task.
Home-page: https://github.com/massivetexts/open-scoring
Author: Peter Organisciak
Author-email: peter.organisciak@du.edu
License: MIT
Classifier: Intended Audience :: Education
Classifier: Natural Language :: English
Classifier: License :: OSI Approved :: MIT License
Classifier: Operating System :: Unix
Classifier: Operating System :: POSIX :: Linux
Classifier: Programming Language :: Python :: 3.10
Classifier: Programming Language :: Python :: 3.9
Classifier: Programming Language :: Python :: 3.8
Classifier: Programming Language :: Python :: 3.7
Classifier: Programming Language :: Python :: 3.6
Classifier: Programming Language :: Python :: 3.5
Classifier: Programming Language :: Python :: 3.1
Classifier: Topic :: Text Processing :: Indexing
Classifier: Topic :: Text Processing :: Linguistic
Requires-Dist: numpy
Requires-Dist: pandas
Requires-Dist: spacy
Requires-Dist: gensim
Requires-Dist: inflect
Requires-Dist: openai
Requires-Dist: tqdm
